[
  {
    "search_keyword": "stage data Science",
    "title": "Stage PFE : IA / NLP — Fine-Tuning à partir de PDFs\n- job post",
    "company": "Koding Schools",
    "location": "Remote",
    "description": "Offre de Stage : IA / NLP — Fine-Tuning à partir de PDFs\nKoding Schools, basée à Marrakech, évolue dans le domaine de la Ed-Tech et conçoit des solutions innovantes d’apprentissage digital intégrées à WordPress, LearnDash et BuddyBoss.\nDans le cadre du développement de nos outils pédagogiques, Koding Schools recherche un(e) stagiaire passionné(e) par l’IA, le traitement du langage naturel (NLP) et les modèles LLM, pour travailler sur la création d’un assistant intelligent entraîné sur nos contenus internes.\nCe que nous offrons :\n● Une mission à impact dans le domaine de l’éducation digitale\n● Un travail stimulant autour des IA modernes (Mistral, Phi, Falcon…)\n● Une autonomie totale en télétravail (100 %)\n● Un environnement technique basé sur WordPress, LearnDash & Python\n● La possibilité de travailler sur un projet concret utilisé par nos élèves\n● Encadrement par l’équipe technique Koding Schools\n● Une ambiance bienveillante et axée sur la créativité\nCe que nous recherchons :\n● Un(e) étudiant(e) curieux(se), autonome et motivé(e) par les technologies IA\n● À l’aise avec l’extraction de données, Python, et le NLP\n● Capable d’apprendre rapidement et de proposer ses propres idées\n● Bonne communication et sens du travail en équipe\nCompétences techniques attendues :\nTraitement IA / NLP\n● Python (indispensable)\n● Bibliothèques d’extraction PDF : PyMuPDF, pdfplumber, PDFMiner\n● Connaissance des workflows NLP (préprocessing, tokenisation, datasets)\n● Notions de fine-tuning LLM (HuggingFace, OpenAI, GanzAI…)\n]● Compréhension des modèles modernes : Deepseek , Mistral, Phi, Falcon, etc.\nDéveloppement & Intégration\n● Notions d’API REST (PHP ou Python)\n● Connaissance de WordPress est un plus\n● Intégration web (Elementor, LearnDash) — bonus\n● Git / GitHub (CI/CD simple apprécié)\nInfrastructure / DevOps (Bonus)\n● Utilisation de plateformes d’entraînement (Colab, AWS, HF Spaces)\n● Notions de sécurité & optimisation\nProfil recherché :\n● Étudiant(e) en informatique / IA / Data Science\n● À l’aise avec Python et l’extraction de données\n● Sensibilité pour l’IA générative et les modèles LLM\n● Force de proposition pour améliorer nos outils IA\n● Capacité à produire documentation et livrables structurés\nMission du stage (Roadmap)\nPhase 1 — Exploration & Définition (Sem. 1–2)\nDécouverte WordPress, LearnDash, WPML\nAnalyse des PDFs des leçons LearnDash\nDéfinition du format dataset (JSON, YAML…)\nPhase 2 — Extraction & Structuration (Sem. 3–4)\nExtraction texte (PyMuPDF, pdfplumber…)\nNettoyage : titres, paragraphes, QCM\nTransformation en Q/A ou passages contextuels\nPhase 3 — Fine-tuning (Sem. 5–8)\nChoix du modèle (Mistral, Phi…)\nGénération dataset compatible fine-tuning\nEntraînement + évaluation (hallucinations, précision)\nPhase 4 — Intégration WordPress (Sem. 9–10)\nCréation API REST sécurisée\nIntégration via plugin ou backend Python\nWidget Elementor ou block LearnDash d’interaction\nPhase 5 — Finalisation (Sem. 11–12)\nTests multi-langues avec WPML\nSécurité, mise en production, rollback\nDocumentation complète + rapport final\nLivrables attendus :\n● Script d’extraction PDF LearnDash\n● Dataset JSON structuré (Q/A ou passages)\n● Modèle fine-tuné + rapport d’évaluation\n● API sécurisée WordPress\n● Démo fonctionnelle (staging KodingSchools)\n● Documentation technique & bilan de stage\nLangages & technologies :\nPython, NLP, Transformers, HuggingFace, WordPress (base), PHP (API), JSON, GitHub, LearnDash, WPML.\nType de contrat :\nStage — 3 à 6 mois\nInformations complémentaires :\nTélétravail 100 %\nDébut : immédiat\nIndemnisation : selon profil\nEnvoyez votre CV à hello@kodingschools.com avec comme objet : Stage PFE : IA / NLP\nJob Type: Internship\nContract length: 6 months",
    "job_url": "https://ma.indeed.com/rc/clk?jk=20cdaba4e8848cbe&bb=-DYsGAxr8G7XZUs76IB1d7ot3GTbb7JiaTpZ6SzJy68cdIsYMvuoB7OvzUlwpViojVN7P_vmgZbBU1lp_uAUnME0c7VjrDb_3aT93qNvurJUkAHymQ3ARhy4LNhmUCb_KAkMCaN-Mm7IAFb75mwL871RFTTInER_&xkcb=SoBe67M3qmR1rST4kZ0KbzkdCdPP&fccid=39d680ec11bc46bf&cmp=Koding-Schools&ti=Stage+Pfe+%3A+Ia+%2F+Nlp+%E2%80%94+Fine-tuning+%C3%80+Partir+De+Pdfs&vjs=3",
    "apply_url": "",
    "extract_date": "2025-11-29",
    "type_poste": "stage",
    "mode_travail": "remote",
    "competences_techniques": [
      "Python",
      "NLP",
      "Transformers",
      "HuggingFace",
      "WordPress",
      "PHP",
      "JSON",
      "GitHub",
      "LearnDash",
      "WPML",
      "PyMuPDF",
      "pdfplumber",
      "PDFMiner"
    ],
    "competences_soft": [
      "travail en équipe",
      "communication",
      "autonomie",
      "curiosité",
      "motivation"
    ],
    "nice_to_have_skills": [
      "connaissance de WordPress",
      "intégration web (Elementor, LearnDash)",
      "Git / GitHub (CI/CD simple apprécié)",
      "utilisation de plateformes d'entraînement (Colab, AWS, HF Spaces)",
      "notions de sécurité & optimisation"
    ],
    "remuneration": "selon profil",
    "missions_principales": [
      "Création d'un assistant intelligent entraîné sur les contenus internes de Koding Schools",
      "Extraction de données à partir de PDFs",
      "Fine-tuning de modèles LLM",
      "Intégration de l'assistant intelligent dans WordPress",
      "Documentation complète et rapport final"
    ],
    "score_embedding": 0.7765262722969055,
    "score_rules": {
      "score_skills": 0.3333333333333333,
      "score_mode_travail": 1.0,
      "score_location": 1.0,
      "score_remuneration": 0.0
    },
    "score_final": 0.6992490967114766
  },
  {
    "search_keyword": "stage data Science",
    "title": "Data Scientist / Ingénieur IA Confirmé (3 à 6 ans d’expérience) – 100 % Remote\n- job post",
    "company": "AdmitEase",
    "location": "Casablanca",
    "description": "À propos de Talio Talent\nTalio Talent est une startup française qui connecte les talents tech d’Afrique et du Moyen-Orient avec des startups et scale-ups européennes à la recherche de profils confirmés pour des missions à distance.\nNotre mission : révéler le potentiel des talents francophones en leur offrant des opportunités internationales 100 % remote, tout en aidant les entreprises à accélérer leur croissance grâce à des profils techniques expérimentés, coachés et accompagnés.\nDescription du poste\nRejoins une startup française innovante et contribue à des projets concrets autour de la data science, de l’intelligence artificielle et de l’automatisation.\nEn tant que Data Scientist / Ingénieur IA confirmé(e), tu participeras activement à la conception, au développement et au déploiement de solutions data-driven pour des startups françaises et européennes.\nTes missions\nConcevoir et implémenter des modèles de Machine Learning et Deep Learning pour répondre à des problématiques métiers variées (prédiction, classification, NLP, computer vision, etc.)\nConstruire et maintenir des pipelines de données robustes et scalables\nAutomatiser les processus d’analyse et de reporting via des outils et frameworks modernes\nCollaborer avec les équipes produit et tech pour définir les besoins et transformer les insights en solutions concrètes\nAssurer la qualité, la traçabilité et la sécurité des données\nEncadrer ou accompagner des profils juniors lorsque nécessaire\nEffectuer une veille active sur les avancées en IA, LLMs, MLOps et Data Engineering\nProfil recherché\nDiplôme d’ingénieur ou Master (Bac+5) en Data Science, IA, informatique ou ingénierie\n3 à 6 ans d’expérience professionnelle en data science, machine learning ou ingénierie de données\nExcellente maîtrise de Python et de ses principales librairies data (Pandas, NumPy, Scikit-learn, TensorFlow, PyTorch, etc.)\nSolides compétences en bases de données (SQL / NoSQL) et en déploiement de modèles (API, Docker, cloud, etc.)\nBonne compréhension des enjeux business et capacité à vulgariser les résultats\nAutonomie, esprit analytique, rigueur et goût pour le travail collaboratif à distance\nCe que nous offrons\nProjets à fort impact dans des environnements innovants (startups, scale-ups, SaaS, fintech, healthtech, etc.)\nExpérience internationale et possibilité de collaborer avec des équipes multiculturelles\nMission 100 % remote avec flexibilité et autonomie\nAccompagnement personnalisé (coaching technique, suivi de mission, communauté d’experts)\nRémunération compétitive, selon expérience et expertise\nType de contrat\nCDI, CDD ou mission freelance – temps plein / remote\nType d'emploi : CDI, CDD, Profession libérale, Stage, Apprentissage / Alternance\nDurée du contrat : 6 mois\nRémunération : à partir de 5.000,00DH par mois",
    "job_url": "https://ma.indeed.com/rc/clk?jk=8f7e8b618ce2f864&bb=-DYsGAxr8G7XZUs76IB1d9Jdt-GJicUDwMuh8TZQuy2Q0YVKmQK50LVKsPwAg5E8w9ec8t7iAzoI-Es_FLlD4ninc04OjqlN7NlC64yUSO0enkcT7IoiiZ-PJkLvyxPbmjGJOfAFU_xN6YfiEHLIH-19K8MRAdHl&xkcb=SoB367M3qmR1rST4kZ0IbzkdCdPP&fccid=85205e3b730b299a&cmp=AdmitEase&ti=Data+Scientist&vjs=3",
    "apply_url": "",
    "extract_date": "2025-11-29",
    "type_poste": "emploi",
    "mode_travail": "remote",
    "competences_techniques": [
      "Python",
      "Pandas",
      "NumPy",
      "Scikit-learn",
      "TensorFlow",
      "PyTorch",
      "SQL",
      "NoSQL",
      "API",
      "Docker",
      "Cloud"
    ],
    "competences_soft": [
      "autonomie",
      "esprit analytique",
      "rigueur",
      "travail collaboratif à distance",
      "vulgarisation des résultats"
    ],
    "nice_to_have_skills": [],
    "remuneration": "à partir de 5.000,00DH par mois",
    "missions_principales": [
      "Concevoir et implémenter des modèles de Machine Learning et Deep Learning",
      "Construire et maintenir des pipelines de données robustes et scalables",
      "Automatiser les processus d’analyse et de reporting",
      "Collaborer avec les équipes produit et tech pour définir les besoins",
      "Assurer la qualité, la traçabilité et la sécurité des données",
      "Encadrer ou accompagner des profils juniors lorsque nécessaire",
      "Effectuer une veille active sur les avancées en IA, LLMs, MLOps et Data Engineering"
    ],
    "score_embedding": 0.743904709815979,
    "score_rules": {
      "score_skills": 0.3333333333333333,
      "score_mode_travail": 1.0,
      "score_location": 1.0,
      "score_remuneration": 0.0
    },
    "score_final": 0.6796761592229208
  },
  {
    "search_keyword": "stage data Science",
    "title": "Stage/PFE Ingénieur IA & Automatisation – NLP & optimisation pour un SaaS\n- job post",
    "company": "PIONOVAAI",
    "location": "Maroc",
    "description": "PIONOVAAI\nMaroc\nStage\nÀ distance\nil y a 2 jour(s)\n\nPionovaAI est une startup marocaine spécialisée dans l’automatisation intelligente des processus métier grâce à l’IA.\nNous développons un SaaS innovant destiné à optimiser et digitaliser les opérations métiers.\n– Missions principales:\nDévelopper des fonctionnalités IA appliquées au produit\nTravailler sur l’analyse, le résumé automatique et le traitement des données\nMettre en place des algorithmes d’optimisation et de recommandations\nContribuer à l’intelligence globale du SaaS\n– Profil recherché:\nÉtudiant(e) en 5e année IA / Data Science\nMaîtrise du Python et des bases du NLP / ML\nMotivation, curiosité et autonomie\nBonus : projets personnels en IA ou optimisation\n– Avantages:\nApplication concrète de l’IA\nMentorat direct avec le fondateur\nPortfolio fort avec un vrai MVP IA\nForte probabilité d’embauche\n– Informations:\nStage / PFE – 4 à 6 mois\n100 % télétravail (le projet étant piloté depuis la France, nous fonctionnons entièrement à distance avec des outils collaboratifs très efficaces)\nDébut : Janvier – Février 2026",
    "job_url": "https://ma.indeed.com/rc/clk?jk=4cffc02e663f7c43&bb=-DYsGAxr8G7XZUs76IB1d2js4ju5gAOsefiH9WAVwvi_AJR1--MyUtWmY8gek79fef_a8io0LQ4ZsTcwKb1BUEh1mdZsEq8_TpdiUOO5oqdGzh4wqA3Ga31Cd_otdRS00OMVZRMsDqP5mVGZEVcXER4C9B8GW858&xkcb=SoA567M3qmR1rST4kZ0CbzkdCdPP&fccid=ebb2b7acb20f2f19&vjs=3",
    "apply_url": "https://ma.indeed.com/applystart?jk=4cffc02e663f7c43&from=vj&pos=bottom&mvj=0&jobsearchTk=1jb6cujj5ha9789l&spon=0&xkcb=SoA567M3qmR1rST4kZ0CbzkdCdPP&xfps=4da5cd9f-c952-4e34-af79-3b648fffe60f&vjfrom=vjs&asub=mob&astse=8e7a6850f7b9b3f0&assa=9429",
    "extract_date": "2025-11-29",
    "type_poste": "stage",
    "mode_travail": "remote",
    "competences_techniques": [
      "Python",
      "NLP",
      "ML"
    ],
    "competences_soft": [
      "motivation",
      "curiosité",
      "autonomie"
    ],
    "nice_to_have_skills": [
      "projets personnels en IA ou optimisation"
    ],
    "remuneration": "stage rémunéré",
    "missions_principales": [
      "Développer des fonctionnalités IA appliquées au produit",
      "Travailler sur l’analyse, le résumé automatique et le traitement des données",
      "Mettre en place des algorithmes d’optimisation et de recommandations",
      "Contribuer à l’intelligence globale du SaaS"
    ],
    "score_embedding": 0.7864932715892792,
    "score_rules": {
      "score_skills": 0.3333333333333333,
      "score_mode_travail": 1.0,
      "score_location": 0.0,
      "score_remuneration": 0.0
    },
    "score_final": 0.6552292962869009
  },
  {
    "search_keyword": "stage data Science",
    "title": "Stage pré-embauche Data Engineer (GCP & Terraform) – 3 mois\n- job post",
    "company": "Metaverse",
    "location": "Casablanca",
    "description": "À propos de nous :\nMetaverse est une organisation tournée vers l'avenir, engagée en faveur de l'innovation et de la technologie. Nous nous consacrons à la création de solutions de pointe qui ont un impact dans divers secteurs. Alors que nous continuons à grandir, nous recherchons des talents motivés et enthousiastes pour rejoindre notre équipe.\nAperçu du poste :\nNous recherchons un(e) Stagiaire Data Engineer (GCP) – Stage pré-embauche de 3 mois pour travailler en étroite collaboration avec notre équipe d'ingénierie des données. Ce stage offre une excellente opportunité pour les aspirant(e)s ingénieurs des données d'acquérir une expérience pratique, s’intégrer au projet client, et préparer une embauche future.\nResponsabilités principales :\nCollaborer avec les ingénieurs seniors pour concevoir, construire et maintenir des pipelines de données et des processus ETL.\nParticiper à l'intégration et à la transformation de données provenant de diverses sources.\nContribuer à l'optimisation et à l'amélioration des performances des pipelines existants.\nAider au développement et à la maintenance des entrepôts de données et bases de données.\nTravailler avec les analystes et scientifiques des données pour garantir la disponibilité et la fiabilité des données.\nDocumenter et communiquer les processus et bonnes pratiques en ingénierie des données.\nParticiper à la gestion de l’infrastructure via des outils d’infrastructure as code, notamment Terraform.\nQualifications :\nÉtudiant(e) en dernière année de Master (BAC+5) en Informatique, Data Engineering ou filière technique connexe, ou diplômé(e) récemment.\nFort intérêt pour l'ingénierie des données et les technologies associées.\nMaîtrise de Python, SQL, Google Cloud Platform (GCP), AWS, Apache Spark et Terraform (obligatoire).\nFamiliarité avec la science des données, les processus ETL, le NLP et le Machine Learning.\nBonnes compétences en résolution de problèmes et sens du détail.\nCapacités de communication et esprit d'équipe.\nModalités du stage pré-embauche :\nDurée : 3 mois\nStage d’intégration sur projet client, en vue d’une embauche éventuelle à l’issue du stage.\nPériode à discuter selon disponibilité.\nLocalisation : Casablanca, Maroc.\nComment postuler ?\nEnvoyez votre CV à recruitment@metave.us en mentionnant l’objet :\n\"Candidature – Stage pré-embauche Data Engineer\".\nInformations complémentaires :\nHoraires : Lundi - Vendredi (9h - 17h) / Samedi (9h - 13h en télétravail)\nDisponibilité : Immédiate\nType d'emploi : Temps plein (stage)\nType d'emploi : Temps plein",
    "job_url": "https://ma.indeed.com/rc/clk?jk=5eae3dc9219a7a1b&bb=-DYsGAxr8G7XZUs76IB1d1sc3MvG83AQiWRSPZO1L8-p_nVg-C9avu_PAgd7_vPaZ4iNe8bqYNGewuIqjXc3ZT7msXkfTurn2GgMgG59VdLGQ7kHMi_tWjzS-Rrfp38dsuskWn4k6Lxa8vjie4jpWkZTyszED-Qm&xkcb=SoDQ67M3qmR1rST4kZ0NbzkdCdPP&fccid=941c1eb24f109b88&cmp=Metaverse&ti=Data+Scientist&vjs=3",
    "apply_url": "",
    "extract_date": "2025-11-29",
    "type_poste": "stage",
    "mode_travail": "hybride",
    "competences_techniques": [
      "Python",
      "SQL",
      "Google Cloud Platform (GCP)",
      "Terraform",
      "Apache Spark"
    ],
    "competences_soft": [
      "Résolution de problèmes",
      "Communication",
      "Esprit d'équipe"
    ],
    "nice_to_have_skills": [
      "Science des données",
      "Processus ETL",
      "NLP",
      "Machine Learning"
    ],
    "remuneration": "",
    "missions_principales": [
      "Collaborer avec les ingénieurs seniors pour concevoir, construire et maintenir des pipelines de données et des processus ETL.",
      "Participer à l'intégration et à la transformation de données provenant de diverses sources.",
      "Contribuer à l'optimisation et à l'amélioration des performances des pipelines existants.",
      "Aider au développement et à la maintenance des entrepôts de données et bases de données.",
      "Travailler avec les analystes et scientifiques des données pour garantir la disponibilité et la fiabilité des données.",
      "Documenter et communiquer les processus et bonnes pratiques en ingénierie des données.",
      "Participer à la gestion de l’infrastructure via des outils d’infrastructure as code, notamment Terraform."
    ],
    "score_embedding": 0.692839041352272,
    "score_rules": {
      "score_skills": 0.3333333333333333,
      "score_mode_travail": 1.0,
      "score_location": 1.0,
      "score_remuneration": 0.0
    },
    "score_final": 0.6490367581446965
  },
  {
    "search_keyword": "stage data Science",
    "title": "Opportunité de Stage – Développeur Full Stack & IA – Rémunéré\n- job post",
    "company": "Smilycall",
    "location": "Marrakech",
    "description": "Smilycall le leader du télésecrétariat qui révolutionne l'accompagnement administratif grâce à la digitalisation et l'intelligence artificielle.\nNous recherchons un talent d'exception.\nUn(e) Développeur(se) Full Stack passionné(e) par l'IA et l'automatisation, prêt(e) à relever un vrai défi : construire des solutions digitales innovantes qui transforment radicalement la manière dont nous gérons les services de télésecrétariat.\nCe stage n'est pas un simple projet de fin d'études — c'est une immersion dans une entreprise visionnaire où tu développeras des outils concrets, intégreras l'IA pour automatiser des processus complexes, et participeras à la transformation digitale d'un secteur entier.\nProfil recherché\nIngénieur ou Master en Informatique / Génie Logiciel / Data Science (Bac+5) Maîtrise du développement Full Stack (Front-end + Back-end) Notions solides en Intelligence Artificielle et Machine Learning Passionné(e) par l'automatisation, les API et l'innovation technologique Capable de transformer un besoin métier en solution technique élégante Esprit analytique, créatif et orienté résolution de problèmes Autonome, rigoureux(se) et avide d'apprendre\nTes futures missions\nDéveloppement & Digitalisation\nConcevoir et développer des applications web pour digitaliser nos processus de télésecrétariat\nCréer des interfaces utilisateurs intuitives et performantes (dashboards, CRM, outils de gestion)\nDévelopper des API robustes pour connecter nos différents systèmes\nOptimiser et maintenir notre infrastructure technique\nIA & Automatisation\nIntégrer des solutions d'IA pour automatiser des tâches répétitives (traitement d'emails, classification de documents, chatbots)\nDévelopper des systèmes de reconnaissance vocale et de transcription automatique\nImplémenter des outils d'analyse de données et de prédiction\nCréer des workflows intelligents pour améliorer l'efficacité opérationnelle\nInnovation Continue\nFaire de la veille technologique sur les nouvelles solutions IA/automatisation\nProposer et prototyper des innovations qui donnent un avantage concurrentiel\nParticiper à l'architecture et à la stratégie technique de l'entreprise\nStack technique recherchée\nFront-end :\nJavaScript / TypeScript (React, Svelte)\nHTML5, CSS3, Tailwind CSS\nResponsive Design & UX/UI\nBack-end :\nNode.js, Python\nAPIs REST\nBases de données (MySQL, PostgreSQL, MongoDB)\nIA & Automatisation :\nPython (TensorFlow, PyTorch, scikit-learn)\nAPIs IA (OpenAI, Google Cloud AI)\nAutomatisation ( n8n)\nNLP (Natural Language Processing)\nConditions\nLieu : Marrakech + télétravail partiel\nRémunération : Attractive + primes sur objectifs\nDurée : 2 a 6 mois (stage pré-embauche)\nCDI garanti à l'issue du stage pour les profils performants\nPourquoi nous rejoindre ?\nParce que tu ne coderas pas \"juste pour coder\", mais pour créer des solutions qui ont un impact réel et immédiat.\nIci, tu auras : L'autonomie de proposer et implémenter tes propres idées L'impact direct sur la croissance de l'entreprise L'apprentissage continu avec des technologies de pointe (IA, automatisation) La reconnaissance : ton talent sera valorisé et récompensé par un CDI\nTu ne seras pas un développeur parmi d'autres — tu seras l'architecte de notre transformation digitale.\nCandidature :\nEnvoie ton CV + Portfolio GitHub (projets, repos, contributions) à : talents@smilycall.com\nObjet : \"Développeur Full Stack & IA - [Ton Prénom]\"\nBonus : Un projet personnel en IA/automatisation ou un lien vers une démo de tes réalisations.\nSeuls les profils les plus prometteurs seront contactés pour un entretien technique.\nNous recherchons l'excellence, pas la moyenne. Si tu es prêt(e) à construire l'avenir du télésecrétariat avec la tech et l'IA, cette opportunité est pour toi.\nType d'emploi : Temps plein, Stage\nDurée du contrat : 6 mois",
    "job_url": "https://ma.indeed.com/rc/clk?jk=70e4b9d83132dada&bb=-DYsGAxr8G7XZUs76IB1dzR2AVwLZthnttMh7UnlABaZt32Hg7FfXu3kjIipkOHt7hgDJ65HKBTzEWKFRTYu9S8eNcoiH2SCORYQ0GajqENrL3ROftWXbhHed7bm3YDose8waLv0Au6znF98lGZDBQLOxIfv5f7_&xkcb=SoBN67M3qmR1rST4kZ0ObzkdCdPP&fccid=e7fba0f396b07df8&cmp=Smilycall&ti=D%C3%A9veloppeur+Full+Stack&vjs=3",
    "apply_url": "",
    "extract_date": "2025-11-29",
    "type_poste": "stage",
    "mode_travail": "hybride",
    "competences_techniques": [
      "JavaScript",
      "TypeScript",
      "React",
      "Svelte",
      "HTML5",
      "CSS3",
      "Tailwind CSS",
      "Node.js",
      "Python",
      "APIs REST",
      "MySQL",
      "PostgreSQL",
      "MongoDB",
      "TensorFlow",
      "PyTorch",
      "scikit-learn",
      "OpenAI",
      "Google Cloud AI",
      "n8n",
      "Natural Language Processing"
    ],
    "competences_soft": [
      "travail en équipe",
      "communication",
      "autonomie",
      "esprit analytique",
      "créativité",
      "orienté résolution de problèmes"
    ],
    "nice_to_have_skills": [],
    "remuneration": "Attractive + primes sur objectifs",
    "missions_principales": [
      "Concevoir et développer des applications web pour digitaliser les processus de télésecrétariat",
      "Créer des interfaces utilisateurs intuitives et performantes",
      "Développer des API robustes pour connecter les différents systèmes",
      "Intégrer des solutions d'IA pour automatiser des tâches répétitives",
      "Développer des systèmes de reconnaissance vocale et de transcription automatique",
      "Implémenter des outils d'analyse de données et de prédiction",
      "Créer des workflows intelligents pour améliorer l'efficacité opérationnelle"
    ],
    "score_embedding": 0.7754011750221252,
    "score_rules": {
      "score_skills": 0.3333333333333333,
      "score_mode_travail": 1.0,
      "score_location": 0.0,
      "score_remuneration": 0.0
    },
    "score_final": 0.6485740383466084
  },
  {
    "search_keyword": "stage data Science",
    "title": "Stage PFE – Développeur IA (Web & Mobile)\n- job post",
    "company": "MAJJANE AGENCY",
    "location": "Rabat",
    "description": "Description du poste :\nMajjane, agence web et communication digitale basée à Rabat, recrute un(e) stagiaire PFE (Bac+5) en Intelligence Artificielle appliquée au développement web & mobile.\nTu intégreras une équipe passionnée par l’innovation et la technologie, et tu participeras activement à la création de fonctionnalités intelligentes intégrées dans des sites web et applications mobiles sur mesure.\nMissions principales :\nDévelopper et intégrer des modules IA dans des plateformes web et mobiles (Laravel, Flutter, React, etc.)\nExploiter et connecter des API d’intelligence artificielle (OpenAI, Google Cloud AI, Hugging Face, etc.)\nParticiper à la création de chatbots, assistants virtuels et fonctionnalités prédictives.\nCollaborer avec les équipes de design et de développement pour améliorer l’expérience utilisateur grâce à l’IA.\nEffectuer une veille technologique sur les dernières innovations en IA appliquées au web et mobile.\nProfil recherché :\nÉtudiant(e) en Bac+5 (école d’ingénieurs / université) en informatique, IA, data science ou développement web & mobile.\nBonnes connaissances en développement web (PHP / Laravel, JavaScript, React, Node.js) et/ou mobile (Flutter, Kotlin, Swift).\nIntérêt marqué pour l’IA appliquée et l’automatisation.\nNotions de Python, machine learning ou intégration d’API IA appréciées.\nConnaissances des API REST, des architectures front/back, et des flux CI/CD.\nCuriosité, rigueur, autonomie et esprit d’équipe.\nCe que nous offrons :\nEncadrement technique & méthodologique par des ingénieurs expérimentés.\nProjet PFE structuré et valorisable (code, doc, démonstrations).\nEnvironnement stimulant, orienté projets réels (clients Maroc & international).\nPour postuler :\nEnvoyez votre CV à rh@majjane.ma avec l’objet «Stage – Développement IA Web & Mobile»\nType d'emploi : Temps plein",
    "job_url": "https://ma.indeed.com/rc/clk?jk=fa473351d6af93eb&bb=-DYsGAxr8G7XZUs76IB1dzt8qN46omjxPoFVbgXLwiYAaWtGATL00RS10qPCMRvmhqK02wIyOvdQ8som4ze7SINlBhzNJRlvl9l0s5cSXZPSdgDD5zB0Cyd2YjQSc8wss3brRCIHgnFj0iPctXJF8nv947I7gzWH&xkcb=SoBk67M3qmR1rST4kZ0MbzkdCdPP&fccid=d7fe37abf462aefd&cmp=MAJJANE-AGENCY&ti=Stagiaire+D%C3%A9veloppeur+Web&vjs=3",
    "apply_url": "",
    "extract_date": "2025-11-29",
    "type_poste": "stage",
    "mode_travail": "presentiel",
    "competences_techniques": [
      "PHP",
      "Laravel",
      "JavaScript",
      "React",
      "Node.js",
      "Flutter",
      "Kotlin",
      "Swift",
      "Python",
      "Machine Learning",
      "API IA",
      "API REST",
      "Architectures front/back",
      "Flux CI/CD"
    ],
    "competences_soft": [
      "Curiosité",
      "Rigueur",
      "Autonomie",
      "Esprit d'équipe"
    ],
    "nice_to_have_skills": [],
    "remuneration": "stage rémunéré",
    "missions_principales": [
      "Développer et intégrer des modules IA dans des plateformes web et mobiles",
      "Exploiter et connecter des API d’intelligence artificielle",
      "Participer à la création de chatbots, assistants virtuels et fonctionnalités prédictives",
      "Collaborer avec les équipes de design et de développement pour améliorer l’expérience utilisateur grâce à l’IA",
      "Effectuer une veille technologique sur les dernières innovations en IA appliquées au web et mobile"
    ],
    "score_embedding": 0.807774007320404,
    "score_rules": {
      "score_skills": 0.3333333333333333,
      "score_mode_travail": 0.2,
      "score_location": 1.0,
      "score_remuneration": 0.0
    },
    "score_final": 0.6379977377255758
  },
  {
    "search_keyword": "stage data Science",
    "title": "Data & AI-Internship Program\n- job post",
    "company": "Capgemini Engineering",
    "location": "Casablanca",
    "description": "Capgemini Engineering, leader mondial des services d'ingénierie, rassemble des équipes d'ingénieurs, de scientifiques et d'architectes pour aider les entreprises les plus innovantes dans le monde à libérer leur potentiel. Des voitures autonomes aux robots qui sauvent des vies, nos experts en technologies digitales et logicielles sortent des sentiers battus en fournissant des services uniques de R&D et d'ingénierie dans tous les secteurs d'activité. Rejoignez-nous pour une carrière pleine d'opportunités, où vous pouvez faire la différence et où aucun jour ne se ressemble.\nA propos du stage\nNous sommes à la recherche d’un(e ) stagiaire PFE passionné(e) pour rejoindre notre équipe Data & AI en tant que Data & AI Intern – Automotive Systems. Ce stage représente une opportunité unique d’acquérir une expérience concrète dans le domaine de la donnée et de l’intelligence artificielle appliquées aux systèmes automobiles, en participant à des projets variés allant de la collecte et l’analyse de données techniques à la mise en œuvre de solutions intelligentes pour l’optimisation des performances mécaniques.\nLieu : Casablanca\nDurée : 6 mois, à partir de février\nNiveau : Étudiant(e) en Master ou équivalent ( Data science, ingénierie mécanique, ou domaine connexe)\nLangues : Bon niveau en français et en anglais requis\nLes missions du stage\nAnalyse des données mécaniques pour identifier des tendances et anomalies.\nDéveloppement de modèles prédictifs pour la maintenance et la performance.\nIntégrer de nouvelle solutions AI\nParticiper aux projets d'innovation dans le domaine de la gestion de la data BOM\n\n\nVotre profil\nÉtudiant(e) en Master : Data science, ingénierie mécanique, systèmes embarqués ou domaine lié aux technologies des véhicule\nIntérêt fort pour l’intelligence artificielle et l’analyse de données appliquées à l’automobile.\nBonne communication écrite et orale .\nAutonomie, rigueur et sens de l’organisation dans la gestion des projets data.\nNos engagements et priorités:\nLe groupe Capgemini encourage une culture inclusive dans un cadre multiculturel et handi-accueillant. En nous rejoignant, vous intégrez un collectif qui valorise la diversité, développe le potentiel de ses talents, s’engage dans des initiatives solidaires avec ses partenaires, et se mobilise pour réduire son impact environnemental sur tous ses sites et auprès de ses clients.\nCapgemini est un leader mondial, responsable et multiculturel, regroupant près de 350 000 personnes dans plus de 50 pays. Fort de 55 ans d’expérience, nous sommes un partenaire stratégique des entreprises pour la transformation de leurs activités en tirant profit de toute la puissance de la technologie et des innovations dans les domaines en perpétuelle évolution tels que le cloud, la data, l’Intelligence Artificielle, la connectivité, les logiciels, l’ingénierie digitale ou les plateformes.",
    "job_url": "https://ma.indeed.com/rc/clk?jk=402984caab7a2b99&bb=-DYsGAxr8G7XZUs76IB1d7ot3GTbb7JiyX8GHY7FUlDyE3gFWMzSgNP9drZgNmj5K5z1N46CiVi3XYtAxlObwoVtTgWmJz_VQu95MfzZ4TZJYZoRoSFzfzLzuuk1GB_bo5ZLOqyThk-Miv0B56YR_A%3D%3D&xkcb=SoDq67M3qmR1rST4kZ0LbzkdCdPP&fccid=80402dcb603cbc8d&vjs=3",
    "apply_url": "https://ma.indeed.com/applystart?jk=402984caab7a2b99&from=vj&pos=bottom&mvj=0&jobsearchTk=1jb6cujj5ha9789l&spon=0&xkcb=SoDq67M3qmR1rST4kZ0LbzkdCdPP&xfps=876e2cd2-5157-4372-b70e-f1f2f9f503fd&vjfrom=vjs&asub=mob&astse=a831463928589722&assa=9256",
    "extract_date": "2025-11-29",
    "type_poste": "stage",
    "mode_travail": "presentiel",
    "competences_techniques": [
      "Python",
      "SQL",
      "Machine Learning",
      "Data Science"
    ],
    "competences_soft": [
      "travail en équipe",
      "communication",
      "autonomie",
      "rigueur",
      "sens de l'organisation"
    ],
    "nice_to_have_skills": [],
    "remuneration": "stage rémunéré",
    "missions_principales": [
      "Analyse des données mécaniques pour identifier des tendances et anomalies.",
      "Développement de modèles prédictifs pour la maintenance et la performance.",
      "Intégrer de nouvelle solutions AI",
      "Participer aux projets d'innovation dans le domaine de la gestion de la data BOM"
    ],
    "score_embedding": 0.7054811269044876,
    "score_rules": {
      "score_skills": 0.5,
      "score_mode_travail": 0.2,
      "score_location": 1.0,
      "score_remuneration": 0.0
    },
    "score_final": 0.6182886761426927
  },
  {
    "search_keyword": "stage data Science",
    "title": "Offre de Stage – Développeur en Intelligence Artificielle (IA)\n- job post",
    "company": "AI HUB",
    "location": "Rabat",
    "description": "Lieu : AI Hub / – Rabat\nDurée : 3 mois\nDébut : Dès que possible\nDescription du poste\nAI Hub propose un stage formateur pour un(e) développeur(euse) en intelligence artificielle passionné(e) par les nouvelles technologies et curieux(se) d’explorer les applications concrètes de l’IA.\nCe stage vous permettra d’acquérir une première expérience pratique au sein d’un environnement innovant et collaboratif.\nMissions principales\nParticiper à la conception et au développement de prototypes d’outils basés sur l’IA\nTravailler sur des projets en lien avec le traitement de données, l’automatisation et le machine learning\nRéaliser des tests et documenter les résultats\nAssister l’équipe technique dans la mise en place de solutions IA internes\nVeille technologique sur les tendances et outils IA\nProfil recherché\nÉtudiant(e) en informatique, data science ou domaine connexe\nConnaissance de base en Python, TensorFlow, ou PyTorch\nIntérêt marqué pour le machine learning, la data et l’automatisation\nEsprit analytique, rigoureux et curieux\nCapacité à travailler en équipe et à apprendre rapidement\nConditions\nStage rémunéré\nAttestation de stage fournie\nHoraires : du lundi au vendredi, 09h00 à 17h30 –\nCandidature\nEnvoyez votre CV à : team@hub4digi.com\nObjet : Stage – Développeur IA\nType d'emploi : Temps plein, Stage\nDurée du contrat : 3 mois\nType d'emploi : Temps plein",
    "job_url": "https://ma.indeed.com/rc/clk?jk=9ee11eddef435923&bb=-DYsGAxr8G7XZUs76IB1d12qh8q1nGt7rWSG6qqYFE-KgDTZRUqpWxp2Y_IOKPATBMkHQQMQTXy_W2LgbLIVdqlKzys0edpl0wIeXKEb6ky83c-L6x6kpHTxIHAZBMrn_laFAYPEWEQD4g92sbmlrEVgVMH9034_&xkcb=SoD567M3qmR1rST4kZ0PbzkdCdPP&fccid=e29cad4ea4d93ed1&cmp=AI-Hub&ti=Stage+D%C3%A9veloppeur&vjs=3",
    "apply_url": "",
    "extract_date": "2025-11-29",
    "type_poste": "stage",
    "mode_travail": "presentiel",
    "competences_techniques": [
      "Python",
      "TensorFlow",
      "PyTorch"
    ],
    "competences_soft": [
      "travail en équipe",
      "communication",
      "autonomie",
      "esprit analytique",
      "rigueur"
    ],
    "nice_to_have_skills": [],
    "remuneration": "stage rémunéré",
    "missions_principales": [
      "Participer à la conception et au développement de prototypes d’outils basés sur l’IA",
      "Travailler sur des projets en lien avec le traitement de données, l’automatisation et le machine learning",
      "Réaliser des tests et documenter les résultats",
      "Assister l’équipe technique dans la mise en place de solutions IA internes",
      "Veille technologique sur les tendances et outils IA"
    ],
    "score_embedding": 0.7611476182937622,
    "score_rules": {
      "score_skills": 0.16666666666666666,
      "score_mode_travail": 0.2,
      "score_location": 1.0,
      "score_remuneration": 0.0
    },
    "score_final": 0.5683552376429241
  },
  {
    "search_keyword": "stage data Science",
    "title": "Société Centrale de Réassurance: Offres de Stages PFE 2025\n- job post",
    "company": "",
    "location": "Casablanca",
    "description": "Description emploi\nDans le cadre de la campagne de stages PFE 2025, la Société Centrale de Réassurance invite les étudiants ambitieux et motivés à intégrer une équipe dynamique et contribuer à des projets de grande envergure. Cette opportunité unique permet de développer des compétences clés tout en travaillant sur des thématiques passionnantes liées aux enjeux actuels.\nEntreprise de référence dans le domaine de la réassurance, la Société Centrale de Réassurance se distingue par son engagement envers l’innovation, la digitalisation et la gestion des risques. En rejoignant ses équipes, les stagiaires bénéficieront d’un encadrement professionnel dans un environnement stimulant et tourné vers l’excellence.\nLes stages proposés couvrent une variété de domaines stratégiques:\nActuariat et Modélisation des Risques\nData Science, IT et Digitalisation\nHydrogéologie et Risques Catastrophiques\nRessources Humaines\nMarketing\nFinance et Contrôle de Gestion\nProfil recherché\nLes candidatures sont ouvertes aux étudiants en fin de cycle, inscrits dans une école d’ingénieurs, une école de commerce ou une université, et souhaitant réaliser leur projet de fin d’études dans l’un des domaines cités ci-dessus.\nQualités attendues:\nEsprit créatif et capacité à proposer des solutions innovantes.\nRéactivité, organisation et autonomie.\nAptitudes analytiques et méthodologie dans la résolution de problèmes.\nExcellentes compétences en communication et en écoute.\nAvantages et perspectives\nRémunération attractive tout au long du stage.\nUne expérience enrichissante avec des projets concrets à fort impact.\nLa possibilité de signer un contrat à la fin du stage, en fonction des performances et de l’adéquation avec les besoins de l’entreprise.\nEn intégrant la Société Centrale de Réassurance, les stagiaires auront l’opportunité d’acquérir une expérience précieuse dans un environnement professionnel de haut niveau, tout en contribuant activement au succès de projets stratégiques.\n\nFinances & Assurances\nStage\n10 mois avant\nCasablanca",
    "job_url": "https://ma.indeed.com/rc/clk?jk=843ecb495d6c416a&bb=-DYsGAxr8G7XZUs76IB1d7ot3GTbb7Jie7AIo6NwCE-l4hse8QdqI1nw1ShNfarVl7nYC4tGQAok_7Tm_jJaaXUyzjRtAMgKzfSF9MkgWAjtNHM7qkZp7R_fQfQivOyZRGUPGlBwmWMAXiRRWCmr_7gmNHaFblOS&xkcb=SoDD67M3qmR1rST4kZ0JbzkdCdPP&fccid=dd616958bd9ddc12&vjs=3",
    "apply_url": "https://ma.indeed.com/applystart?jk=843ecb495d6c416a&from=vj&pos=bottom&mvj=0&jobsearchTk=1jb6cujj5ha9789l&spon=0&xkcb=SoDD67M3qmR1rST4kZ0JbzkdCdPP&xfps=466fc520-33d6-4370-9c84-6943a75ed404&vjfrom=vjs&asub=mob&astse=a30ff791ce32e318&assa=186",
    "extract_date": "2025-11-29",
    "type_poste": "stage",
    "mode_travail": "presentiel",
    "competences_techniques": [],
    "competences_soft": [
      "esprit créatif",
      "capacité à proposer des solutions innovantes",
      "réactivité",
      "organisation",
      "autonomie",
      "aptitudes analytiques",
      "méthodologie dans la résolution de problèmes",
      "excellentes compétences en communication et en écoute"
    ],
    "nice_to_have_skills": [],
    "remuneration": "rémunération attractive tout au long du stage",
    "missions_principales": [
      "Développer des compétences clés tout en travaillant sur des thématiques passionnantes liées aux enjeux actuels",
      "Contribuer à des projets de grande envergure dans différents domaines stratégiques",
      "Acquérir une expérience précieuse dans un environnement professionnel de haut niveau",
      "Contribuer activement au succès de projets stratégiques",
      "Réaliser son projet de fin d’études dans l’un des domaines cités ci-dessus",
      "Développer des compétences en communication et en écoute"
    ],
    "score_embedding": 0.7811598181724548,
    "score_rules": {
      "score_skills": 0.0,
      "score_mode_travail": 0.2,
      "score_location": 1.0,
      "score_remuneration": 0.0
    },
    "score_final": 0.5386958909034729
  },
  {
    "search_keyword": "stage data Science",
    "title": "Stage ingénieur\n- job post",
    "company": "Acti-sens",
    "location": "Kénitra",
    "description": "Entreprise\nActi-Sens est un laboratoire innovant qui explore les interactions entre charge cognitive, prise de décision, et motivation à l’aide de signaux EEG/NIRS et de données comportementales. L’équipe actuelle de stagiaires travaille sur l’analyse de ces signaux via des modèles classiques (SVM, Random Forest…) et profonds (GRU, BiLSTM), avec un fort accent sur l’explicabilité (SHAP) et la reproductibilité scientifique.\nNous collaborons également avec des chercheurs en France et en Italie (Université Paris Nanterre, Université de Padoue) sur des paradigmes cognitifs complexes comme l’apprentissage inversé probabiliste, en situation de double tâche.\nPoste\nEn collaboration avec les membres actuels (profil ingénieur, cognitive science, dev fullstack), vous contribuerez à :\nL’analyse avancée de données EEG/NIRS (prétraitement, extraction de features, fusion multimodale)\nL’expérimentation de modèles hybrides IA pour la prédiction de la charge cognitive et la classification des profils utilisateurs\nLa rédaction d’articles scientifiques (IEEE/Sensors/Frontiers…) en collaboration avec les autres stagiaires\nLa mise en place d’outils collaboratifs (GitHub, ClickUp, Notion) pour le suivi et la transparence des résultats\nLe prototypage éventuel d’une interface web de visualisation (Streamlit ou Dash)\nProfil\nÉtudiant·e en dernière année de cycle ingénieur (informatique, data science, bioinfo, IA ou équivalent)\nAu moins une publication scientifique acceptée dans un journal à comité de lecture, à joindre au CV\nSolide maîtrise de Python (numpy, pandas, scikit-learn, pytorch ou tensorflow)\nExpérience en traitement de signaux (EEG/NIRS ou capteurs physiologiques) appréciée\nAisance avec les outils collaboratifs et autonomie dans le travail en équipe\nIntérêt fort pour la recherche appliquée, les interfaces cerveau-ordinateur et les approches explicables en IA\nLes + de ce stage :\nEncadrement académique rigoureux et possibilité de co-signature sur publications scientifiques\nIntégration dans une équipe jeune, bienveillante et multidisciplinaire\nAccès à des données exclusives et des outils d’analyse avancés (Matlab, EEGLab, Python, EDFBrowser, Homer3, etc.)\nParticipation active à la conception de protocoles expérimentaux et à leur analyse\nSuivi agile : réunions régulières, suivi sur ClickUp, documentation partagée\nLocaux agréables à Kénitra, ambiance conviviale",
    "job_url": "https://ma.indeed.com/rc/clk?jk=7e5a35f5fddaf957&bb=-DYsGAxr8G7XZUs76IB1d7ykLkNlM0yWrkH-RM6JfzRTmE9qsjM5cM6M_2EXlniRT9mDQngl20EMfF_OUjcKrE4s_lHEvJ3eSes23hHCkrZ3IRTQDDS_EOoAQnQJN7x_HAY_uELTi9s8K3-WXmU99J6vtr3IW0wh&xkcb=SoCN67M3qmR1rST4kZ0DbzkdCdPP&fccid=2cc2f834b0d5fed9&vjs=3",
    "apply_url": "https://ma.indeed.com/applystart?jk=7e5a35f5fddaf957&from=vj&pos=bottom&mvj=0&jobsearchTk=1jb6cujj5ha9789l&spon=0&xkcb=SoCN67M3qmR1rST4kZ0DbzkdCdPP&xfps=e83010a0-d082-4846-b973-1d7ca0efb983&vjfrom=vjs&asub=mob&astse=d25f3bd802e3181e&assa=4576",
    "extract_date": "2025-11-29",
    "type_poste": "stage",
    "mode_travail": "presentiel",
    "competences_techniques": [
      "Python",
      "numpy",
      "pandas",
      "scikit-learn",
      "pytorch",
      "tensorflow",
      "EEG/NIRS",
      "Matlab",
      "EEGLab",
      "EDFBrowser",
      "Homer3"
    ],
    "competences_soft": [
      "travail en équipe",
      "autonomie",
      "communication"
    ],
    "nice_to_have_skills": [
      "expérience en traitement de signaux",
      "connaissance des outils collaboratifs"
    ],
    "remuneration": "",
    "missions_principales": [
      "Analyse avancée de données EEG/NIRS",
      "Expérimentation de modèles hybrides IA",
      "Rédaction d'articles scientifiques",
      "Mise en place d'outils collaboratifs",
      "Prototypage d'une interface web de visualisation"
    ],
    "score_embedding": 0.7114790081977844,
    "score_rules": {
      "score_skills": 0.16666666666666666,
      "score_mode_travail": 0.2,
      "score_location": 0.0,
      "score_remuneration": 0.0
    },
    "score_final": 0.48855407158533737
  }
]